{"16312520241821s": {"submission": "1821", "time": 1631252024, "score": 60.0, "extra": ["0", "10", "30", "10", "10", "0"]}, "16312520671822s": {"submission": "1822", "time": 1631252067, "score": 100.0, "extra": ["100"]}, "16312520841823s": {"submission": "1823", "time": 1631252084, "score": 50.0, "extra": ["0", "10", "30", "10", "0", "0"]}, "16312520911824s": {"submission": "1824", "time": 1631252091, "score": 10.0, "extra": ["0", "10", "0", "0", "0", "0"]}, "16312521031825s": {"submission": "1825", "time": 1631252103, "score": 100.0, "extra": ["100"]}, "16312521121826s": {"submission": "1826", "time": 1631252112, "score": 100.0, "extra": ["0", "10", "30", "10", "10", "40"]}, "16312521171827s": {"submission": "1827", "time": 1631252117, "score": 100.0, "extra": ["0", "10", "30", "10", "10", "40"]}, "16312521561828s": {"submission": "1828", "time": 1631252156, "score": 100.0, "extra": ["0", "10", "30", "10", "10", "40"]}, "16312521971829s": {"submission": "1829", "time": 1631252197, "score": 100.0, "extra": ["0", "10", "30", "10", "10", "40"]}, "16312522101830s": {"submission": "1830", "time": 1631252210, "score": 100.0, "extra": ["0", "10", "30", "10", "10", "40"]}, "16312522511831s": {"submission": "1831", "time": 1631252251, "score": 60.0, "extra": ["0", "10", "30", "10", "10", "0"]}, "16312522611832s": {"submission": "1832", "time": 1631252261, "score": 100.0, "extra": ["100"]}, "16312522681833s": {"submission": "1833", "time": 1631252268, "score": 10.0, "extra": ["0", "10", "0", "0", "0", "0"]}, "16312522901834s": {"submission": "1834", "time": 1631252290, "score": 100.0, "extra": ["0", "10", "30", "10", "10", "40"]}, "16312523221835s": {"submission": "1835", "time": 1631252322, "score": 100.0, "extra": ["0", "10", "30", "10", "10", "40"]}, "16312523471836s": {"submission": "1836", "time": 1631252347, "score": 50.0, "extra": ["0", "10", "30", "10", "0", "0"]}, "16312523491837s": {"submission": "1837", "time": 1631252349, "score": 100.0, "extra": ["100"]}, "16312524101838s": {"submission": "1838", "time": 1631252410, "score": 100.0, "extra": ["100"]}, "16312524141839s": {"submission": "1839", "time": 1631252414, "score": 60.0, "extra": ["0", "10", "30", "10", "10", "0"]}, "16312524161840s": {"submission": "1840", "time": 1631252416, "score": 30.0, "extra": ["0", "0", "30", "0", "0", "0"]}, "16312524471841s": {"submission": "1841", "time": 1631252447, "score": 100.0, "extra": ["100"]}, "16312524521842s": {"submission": "1842", "time": 1631252452, "score": 100.0, "extra": ["100"]}, "16312524671843s": {"submission": "1843", "time": 1631252467, "score": 100.0, "extra": ["0", "10", "30", "10", "10", "40"]}, "16312524821844s": {"submission": "1844", "time": 1631252482, "score": 100.0, "extra": ["100"]}, "16312524871845s": {"submission": "1845", "time": 1631252487, "score": 10.0, "extra": ["0", "10", "0", "0", "0", "0"]}, "16312524941846s": {"submission": "1846", "time": 1631252494, "score": 100.0, "extra": ["100"]}, "16312524951848s": {"submission": "1848", "time": 1631252495, "score": 10.0, "extra": ["0", "10", "0", "0", "0", "0"]}, "16312524941847s": {"submission": "1847", "time": 1631252494, "score": 100.0, "extra": ["100"]}, "16312525341849s": {"submission": "1849", "time": 1631252534, "score": 100.0, "extra": ["0", "10", "30", "10", "10", "40"]}, "16312525601850s": {"submission": "1850", "time": 1631252560, "score": 100.0, "extra": ["100"]}, "16312525671851s": {"submission": "1851", "time": 1631252567, "score": 100.0, "extra": ["0", "8", "12", "56", "24"]}, "16312525851852s": {"submission": "1852", "time": 1631252585, "score": 0.0, "extra": ["0", "0", "0", "0", "0", "0"]}, "16312525871853s": {"submission": "1853", "time": 1631252587, "score": 30.0, "extra": ["0", "0", "30", "0", "0", "0"]}, "16312525951854s": {"submission": "1854", "time": 1631252595, "score": 100.0, "extra": ["0", "10", "30", "10", "10", "40"]}, "16312526181855s": {"submission": "1855", "time": 1631252618, "score": 0.0, "extra": ["0", "0", "0", "0", "0", "0"]}, "16312526451856s": {"submission": "1856", "time": 1631252645, "score": 100.0, "extra": ["100"]}, "16312526531857s": {"submission": "1857", "time": 1631252653, "score": 100.0, "extra": ["100"]}, "16312526631858s": {"submission": "1858", "time": 1631252663, "score": 100.0, "extra": ["100"]}, "16312526781859s": {"submission": "1859", "time": 1631252678, "score": 60.0, "extra": ["0", "10", "30", "10", "10", "0"]}, "16312527161860s": {"submission": "1860", "time": 1631252716, "score": 30.0, "extra": ["0", "0", "30", "0", "0", "0"]}, "16312527361861s": {"submission": "1861", "time": 1631252736, "score": 100.0, "extra": ["0", "10", "30", "10", "10", "40"]}, "16312527531862s": {"submission": "1862", "time": 1631252753, "score": 0.0, "extra": ["0", "0", "0", "0", "0", "0"]}, "16312527681863s": {"submission": "1863", "time": 1631252768, "score": 30.0, "extra": ["0", "0", "30", "0", "0", "0"]}, "16312527901864s": {"submission": "1864", "time": 1631252790, "score": 0.0, "extra": ["0", "0", "0", "0", "0", "0"]}, "16312528181865s": {"submission": "1865", "time": 1631252818, "score": 60.0, "extra": ["0", "10", "30", "10", "10", "0"]}, "16312528351866s": {"submission": "1866", "time": 1631252835, "score": 100.0, "extra": ["0", "8", "12", "56", "24"]}, "16312528471867s": {"submission": "1867", "time": 1631252847, "score": 30.0, "extra": ["0", "0", "30", "0", "0", "0"]}, "16312528601868s": {"submission": "1868", "time": 1631252860, "score": 100.0, "extra": ["100"]}, "16312528611869s": {"submission": "1869", "time": 1631252861, "score": 100.0, "extra": ["0", "10", "30", "10", "10", "40"]}, "16312528761871s": {"submission": "1871", "time": 1631252876, "score": 100.0, "extra": ["0", "10", "30", "10", "10", "40"]}, "16312528751870s": {"submission": "1870", "time": 1631252875, "score": 100.0, "extra": ["100"]}, "16312528811872s": {"submission": "1872", "time": 1631252881, "score": 100.0, "extra": ["100"]}, "16312529001873s": {"submission": "1873", "time": 1631252900, "score": 100.0, "extra": ["0", "10", "30", "10", "10", "40"]}, "16312529551874s": {"submission": "1874", "time": 1631252955, "score": 100.0, "extra": ["0", "8", "12", "56", "24"]}, "16312530171875s": {"submission": "1875", "time": 1631253017, "score": 100.0, "extra": ["0", "10", "30", "10", "10", "40"]}, "16312530251876s": {"submission": "1876", "time": 1631253025, "score": 0.0, "extra": ["0", "0", "0", "0", "0", "0"]}, "16312530361877s": {"submission": "1877", "time": 1631253036, "score": 0.0, "extra": ["0", "0", "0", "0", "0", "0"]}, "16312530711878s": {"submission": "1878", "time": 1631253071, "score": 30.0, "extra": ["0", "0", "30", "0", "0", "0"]}, "16312531251879s": {"submission": "1879", "time": 1631253125, "score": 100.0, "extra": ["0", "8", "12", "56", "24"]}, "16312531451880s": {"submission": "1880", "time": 1631253145, "score": 100.0, "extra": ["100"]}, "16312531461881s": {"submission": "1881", "time": 1631253146, "score": 30.0, "extra": ["0", "0", "30", "0", "0", "0"]}, "16312531601882s": {"submission": "1882", "time": 1631253160, "score": 100.0, "extra": ["0", "18", "8", "14", "39", "21"]}, "16312532191883s": {"submission": "1883", "time": 1631253219, "score": 100.0, "extra": ["0", "10", "30", "10", "10", "40"]}, "16312532201884s": {"submission": "1884", "time": 1631253220, "score": 100.0, "extra": ["100"]}, "16312532441885s": {"submission": "1885", "time": 1631253244, "score": 100.0, "extra": ["0", "10", "30", "10", "10", "40"]}, "16312532671886s": {"submission": "1886", "time": 1631253267, "score": 0.0, "extra": ["0", "0", "0", "0", "0", "0"]}, "16312532711887s": {"submission": "1887", "time": 1631253271, "score": 0.0, "extra": ["0", "0", "0", "0", "0", "0"]}, "16312532791888s": {"submission": "1888", "time": 1631253279, "score": 60.0, "extra": ["0", "10", "30", "10", "10", "0"]}, "16312532901889s": {"submission": "1889", "time": 1631253290, "score": 100.0, "extra": ["100"]}, "16312532961890s": {"submission": "1890", "time": 1631253296, "score": 0.0, "extra": ["0", "0", "0", "0", "0", "0"]}, "16312533001891s": {"submission": "1891", "time": 1631253300, "score": 100.0, "extra": ["0", "10", "30", "10", "10", "40"]}, "16312533871892s": {"submission": "1892", "time": 1631253387, "score": 60.0, "extra": ["0", "10", "30", "10", "10", "0"]}, "16312534141893s": {"submission": "1893", "time": 1631253414, "score": 60.0, "extra": ["0", "10", "30", "10", "10", "0"]}, "16312534201894s": {"submission": "1894", "time": 1631253420, "score": 100.0, "extra": ["100"]}, "16312534311895s": {"submission": "1895", "time": 1631253431, "score": 30.0, "extra": ["0", "0", "30", "0", "0", "0"]}, "16312535251896s": {"submission": "1896", "time": 1631253525, "score": 60.0, "extra": ["0", "10", "30", "10", "10", "0"]}, "16312535411897s": {"submission": "1897", "time": 1631253541, "score": 60.0, "extra": ["0", "10", "30", "10", "10", "0"]}, "16312535561898s": {"submission": "1898", "time": 1631253556, "score": 0.0, "extra": ["0"]}, "16312535691899s": {"submission": "1899", "time": 1631253569, "score": 100.0, "extra": ["100"]}, "16312535761900s": {"submission": "1900", "time": 1631253576, "score": 0.0, "extra": ["0", "0", "0", "0", "0", "0"]}, "16312536681901s": {"submission": "1901", "time": 1631253668, "score": 60.0, "extra": ["0", "10", "30", "10", "10", "0"]}, "16312536821903s": {"submission": "1903", "time": 1631253682, "score": 0.0, "extra": ["0"]}, "16312536791902s": {"submission": "1902", "time": 1631253679, "score": 100.0, "extra": ["0", "10", "30", "10", "10", "40"]}, "16312536971904s": {"submission": "1904", "time": 1631253697, "score": 30.0, "extra": ["0", "0", "30", "0", "0", "0"]}, "16312537421906s": {"submission": "1906", "time": 1631253742, "score": 100.0, "extra": ["100"]}, "16312537291905s": {"submission": "1905", "time": 1631253729, "score": 100.0, "extra": ["0", "18", "8", "14", "39", "21"]}, "16312537731907s": {"submission": "1907", "time": 1631253773, "score": 0.0, "extra": ["0", "0", "0", "0", "0", "0"]}, "16312537991908s": {"submission": "1908", "time": 1631253799, "score": 100.0, "extra": ["100"]}, "16312538091909s": {"submission": "1909", "time": 1631253809, "score": 0.0, "extra": ["0", "0", "0", "0", "0", "0"]}, "16312538251910s": {"submission": "1910", "time": 1631253825, "score": 100.0, "extra": ["0", "18", "8", "14", "39", "21"]}, "16312538511911s": {"submission": "1911", "time": 1631253851, "score": 0.0, "extra": ["0"]}, "16312538851912s": {"submission": "1912", "time": 1631253885, "score": 71.0, "extra": ["0", "18", "0", "14", "39", "0"]}, "16312538971913s": {"submission": "1913", "time": 1631253897, "score": 0.0, "extra": ["0", "0", "0", "0", "0", "0"]}, "16312539031914s": {"submission": "1914", "time": 1631253903, "score": 100.0, "extra": ["0", "4", "9", "31", "23", "33"]}, "16312539271915s": {"submission": "1915", "time": 1631253927, "score": 0.0, "extra": ["0", "0", "0", "0", "0", "0"]}, "16312539531916s": {"submission": "1916", "time": 1631253953, "score": 0.0, "extra": ["0", "0", "0", "0", "0", "0"]}, "16312539761917s": {"submission": "1917", "time": 1631253976, "score": 100.0, "extra": ["100"]}, "16312540071918s": {"submission": "1918", "time": 1631254007, "score": 71.0, "extra": ["0", "18", "0", "14", "39", "0"]}, "16312540111919s": {"submission": "1919", "time": 1631254011, "score": 30.0, "extra": ["0", "0", "30", "0", "0", "0"]}, "16312540591920s": {"submission": "1920", "time": 1631254059, "score": 0.0, "extra": ["0", "0", "0", "0", "0", "0"]}, "16312540591921s": {"submission": "1921", "time": 1631254059, "score": 0.0, "extra": ["0", "0", "0", "0", "0", "0"]}, "16312541521922s": {"submission": "1922", "time": 1631254152, "score": 0.0, "extra": ["0", "0", "0", "0", "0", "0"]}, "16312541961923s": {"submission": "1923", "time": 1631254196, "score": 0.0, "extra": ["0", "0", "0", "0", "0", "0"]}, "16312541991924s": {"submission": "1924", "time": 1631254199, "score": 100.0, "extra": ["100"]}, "16312542021925s": {"submission": "1925", "time": 1631254202, "score": 100.0, "extra": ["0", "18", "8", "14", "39", "21"]}, "16312542331926s": {"submission": "1926", "time": 1631254233, "score": 0.0, "extra": ["0", "0", "0", "0", "0", "0"]}, "16312542481927s": {"submission": "1927", "time": 1631254248, "score": 100.0, "extra": ["0", "4", "9", "31", "23", "33"]}, "16312542511928s": {"submission": "1928", "time": 1631254251, "score": 100.0, "extra": ["0", "10", "30", "10", "10", "40"]}, "16312542781929s": {"submission": "1929", "time": 1631254278, "score": 100.0, "extra": ["0", "8", "12", "56", "24"]}, "16312542921930s": {"submission": "1930", "time": 1631254292, "score": 0.0, "extra": ["0", "0", "0", "0", "0", "0"]}, "16312543441931s": {"submission": "1931", "time": 1631254344, "score": 64.0, "extra": ["0", "8", "0", "56", "0"]}, "16312544161932s": {"submission": "1932", "time": 1631254416, "score": 100.0, "extra": ["0", "10", "30", "10", "10", "40"]}, "16312544351933s": {"submission": "1933", "time": 1631254435, "score": 0.0, "extra": ["0", "0", "0", "0", "0", "0"]}, "16312544861934s": {"submission": "1934", "time": 1631254486, "score": 30.0, "extra": ["0", "0", "30", "0", "0", "0"]}, "16312545331935s": {"submission": "1935", "time": 1631254533, "score": 0.0, "extra": ["0", "0", "0", "0", "0", "0"]}, "16312545581936s": {"submission": "1936", "time": 1631254558, "score": 100.0, "extra": ["100"]}, "16312545751937s": {"submission": "1937", "time": 1631254575, "score": 0.0, "extra": ["0"]}, "16312545871938s": {"submission": "1938", "time": 1631254587, "score": 0.0, "extra": ["0", "0", "0", "0", "0", "0"]}, "16312545991939s": {"submission": "1939", "time": 1631254599, "score": 18.0, "extra": ["0", "18", "0", "0", "0", "0"]}, "16312546341940s": {"submission": "1940", "time": 1631254634, "score": 60.0, "extra": ["0", "10", "30", "10", "10", "0"]}, "16312546571942s": {"submission": "1942", "time": 1631254657, "score": 0.0, "extra": ["0", "0", "0", "0", "0", "0"]}, "16312546541941s": {"submission": "1941", "time": 1631254654, "score": 0.0, "extra": ["0", "0", "0", "0", "0", "0"]}, "16312547051943s": {"submission": "1943", "time": 1631254705, "score": 0.0, "extra": ["0", "0", "0", "0", "0", "0"]}, "16312547081944s": {"submission": "1944", "time": 1631254708, "score": 100.0, "extra": ["0", "4", "9", "31", "23", "33"]}, "16312548461945s": {"submission": "1945", "time": 1631254846, "score": 100.0, "extra": ["100"]}, "16312548541946s": {"submission": "1946", "time": 1631254854, "score": 100.0, "extra": ["100"]}, "16312548611947s": {"submission": "1947", "time": 1631254861, "score": 68.0, "extra": ["0", "0", "12", "56", "0"]}, "16312548711948s": {"submission": "1948", "time": 1631254871, "score": 30.0, "extra": ["0", "0", "30", "0", "0", "0"]}, "16312549291949s": {"submission": "1949", "time": 1631254929, "score": 0.0, "extra": ["0", "0", "0", "0", "0"]}, "16312549421950s": {"submission": "1950", "time": 1631254942, "score": 0.0, "extra": ["0", "0", "0", "0", "0", "0"]}, "16312550091951s": {"submission": "1951", "time": 1631255009, "score": 0.0, "extra": ["0", "0", "0", "0", "0", "0"]}, "16312550171952s": {"submission": "1952", "time": 1631255017, "score": 0.0, "extra": ["0", "0", "0", "0", "0", "0"]}, "16312550211953s": {"submission": "1953", "time": 1631255021, "score": 0.0, "extra": ["0", "0", "0", "0", "0", "0"]}, "16312550231954s": {"submission": "1954", "time": 1631255023, "score": 30.0, "extra": ["0", "0", "30", "0", "0", "0"]}, "16312550371955s": {"submission": "1955", "time": 1631255037, "score": 18.0, "extra": ["0", "18", "0", "0", "0", "0"]}, "16312550421956s": {"submission": "1956", "time": 1631255042, "score": 30.0, "extra": ["0", "0", "30", "0", "0", "0"]}, "16312550751957s": {"submission": "1957", "time": 1631255075, "score": 100.0, "extra": ["0", "8", "12", "56", "24"]}, "16312551161958s": {"submission": "1958", "time": 1631255116, "score": 0.0, "extra": ["0", "0", "0", "0", "0", "0"]}, "16312551391959s": {"submission": "1959", "time": 1631255139, "score": 56.0, "extra": ["0", "0", "0", "56", "0"]}, "16312551421960s": {"submission": "1960", "time": 1631255142, "score": 64.0, "extra": ["0", "8", "0", "56", "0"]}, "16312551671961s": {"submission": "1961", "time": 1631255167, "score": 100.0, "extra": ["0", "10", "30", "10", "10", "40"]}, "16312551761962s": {"submission": "1962", "time": 1631255176, "score": 0.0, "extra": ["0", "0", "0", "0", "0", "0"]}, "16312551951963s": {"submission": "1963", "time": 1631255195, "score": 18.0, "extra": ["0", "18", "0", "0", "0", "0"]}, "16312552901964s": {"submission": "1964", "time": 1631255290, "score": 0.0, "extra": ["0", "0", "0", "0", "0", "0"]}, "16312553081965s": {"submission": "1965", "time": 1631255308, "score": 0.0, "extra": ["0", "0", "0", "0", "0", "0"]}, "16312554771966s": {"submission": "1966", "time": 1631255477, "score": 0.0, "extra": ["0", "0", "0", "0", "0", "0"]}, "16312555011967s": {"submission": "1967", "time": 1631255501, "score": 100.0, "extra": ["100"]}, "16312555181968s": {"submission": "1968", "time": 1631255518, "score": 0.0, "extra": ["0", "0", "0", "0", "0", "0"]}, "16312555251969s": {"submission": "1969", "time": 1631255525, "score": 0.0, "extra": ["0", "0", "0", "0", "0", "0"]}, "16312555291970s": {"submission": "1970", "time": 1631255529, "score": 0.0, "extra": ["0", "0", "0", "0", "0", "0"]}, "16312555421971s": {"submission": "1971", "time": 1631255542, "score": 100.0, "extra": ["100"]}, "16312555571972s": {"submission": "1972", "time": 1631255557, "score": 12.0, "extra": ["0", "0", "12", "0", "0"]}, "16312555731973s": {"submission": "1973", "time": 1631255573, "score": 56.0, "extra": ["0", "0", "0", "56", "0"]}, "16312556001974s": {"submission": "1974", "time": 1631255600, "score": 0.0, "extra": ["0", "0", "0", "0", "0"]}, "16312556041975s": {"submission": "1975", "time": 1631255604, "score": 9.0, "extra": ["0", "0", "0", "6", "3", "0", "0", "0", "0"]}, "16312556601976s": {"submission": "1976", "time": 1631255660, "score": 0.0, "extra": ["0", "0", "0", "0", "0", "0"]}, "16312557281977s": {"submission": "1977", "time": 1631255728, "score": 0.0, "extra": ["0", "0", "0", "0", "0", "0"]}, "16312557331978s": {"submission": "1978", "time": 1631255733, "score": 0.0, "extra": ["0", "0", "0", "0", "0"]}, "16312557401979s": {"submission": "1979", "time": 1631255740, "score": 100.0, "extra": ["100"]}, "16312557571980s": {"submission": "1980", "time": 1631255757, "score": 0.0, "extra": ["0", "0", "0", "0", "0"]}, "16312557641981s": {"submission": "1981", "time": 1631255764, "score": 0.0, "extra": ["0", "0", "0", "0", "0", "0", "0", "0", "0"]}, "16312557721982s": {"submission": "1982", "time": 1631255772, "score": 0.0, "extra": ["0", "0", "0", "0", "0", "0"]}, "16312557881984s": {"submission": "1984", "time": 1631255788, "score": 56.0, "extra": ["0", "0", "0", "56", "0"]}, "16312557821983s": {"submission": "1983", "time": 1631255782, "score": 18.0, "extra": ["0", "18", "0", "0", "0", "0"]}, "16312558371985s": {"submission": "1985", "time": 1631255837, "score": 31.0, "extra": ["0", "0", "0", "31", "0", "0"]}, "16312558681986s": {"submission": "1986", "time": 1631255868, "score": 100.0, "extra": ["0", "8", "12", "56", "24"]}, "16312558951987s": {"submission": "1987", "time": 1631255895, "score": 67.0, "extra": ["0", "4", "9", "31", "23", "0"]}, "16312558971988s": {"submission": "1988", "time": 1631255897, "score": 1.0, "extra": ["0", "0", "1", "0", "0", "0", "0", "0", "0"]}, "16312559021989s": {"submission": "1989", "time": 1631255902, "score": 6.0, "extra": ["0", "6", "0", "0", "0"]}, "16312559381990s": {"submission": "1990", "time": 1631255938, "score": 0.0, "extra": ["0", "0", "0", "0", "0", "0"]}, "16312559421991s": {"submission": "1991", "time": 1631255942, "score": 0.0, "extra": ["0", "0", "0", "0", "0", "0"]}, "16312559691992s": {"submission": "1992", "time": 1631255969, "score": 0.0, "extra": ["0", "0", "0", "0", "0", "0"]}, "16312560161993s": {"submission": "1993", "time": 1631256016, "score": 60.0, "extra": ["0", "10", "30", "10", "10", "0"]}, "16312560251995s": {"submission": "1995", "time": 1631256025, "score": 0.0, "extra": ["0", "0", "0", "0", "0", "0"]}, "16312560241994s": {"submission": "1994", "time": 1631256024, "score": 100.0, "extra": ["0", "8", "12", "56", "24"]}, "16312560881996s": {"submission": "1996", "time": 1631256088, "score": 100.0, "extra": ["0", "8", "12", "56", "24"]}, "16312560891997s": {"submission": "1997", "time": 1631256089, "score": 18.0, "extra": ["0", "18", "0", "0", "0", "0"]}, "16312561341998s": {"submission": "1998", "time": 1631256134, "score": 9.0, "extra": ["0", "0", "0", "6", "3", "0", "0", "0", "0"]}, "16312561601999s": {"submission": "1999", "time": 1631256160, "score": 7.0, "extra": ["0", "0", "7", "0", "0"]}, "16312561982000s": {"submission": "2000", "time": 1631256198, "score": 100.0, "extra": ["0", "4", "9", "31", "23", "33"]}, "16312562002001s": {"submission": "2001", "time": 1631256200, "score": 18.0, "extra": ["0", "18", "0", "0", "0", "0"]}, "16312563472002s": {"submission": "2002", "time": 1631256347, "score": 0.0, "extra": ["0", "0", "0", "0", "0", "0"]}, "16312563592003s": {"submission": "2003", "time": 1631256359, "score": 56.0, "extra": ["0", "0", "0", "56", "0"]}, "16312564072004s": {"submission": "2004", "time": 1631256407, "score": 0.0, "extra": ["0", "0", "0", "0", "0", "0", "0", "0", "0"]}, "16312564302005s": {"submission": "2005", "time": 1631256430, "score": 13.0, "extra": ["0", "4", "9", "0", "0", "0"]}, "16312565322006s": {"submission": "2006", "time": 1631256532, "score": 0.0, "extra": ["0", "0", "0", "0", "0", "0", "0", "0", "0"]}, "16312565322007s": {"submission": "2007", "time": 1631256532, "score": 0.0, "extra": ["0", "0", "0", "0", "0", "0"]}, "16312565342008s": {"submission": "2008", "time": 1631256534, "score": 0.0, "extra": ["0", "0", "0", "0", "0", "0"]}, "16312565712009s": {"submission": "2009", "time": 1631256571, "score": 0.0, "extra": ["0", "0", "0", "0", "0", "0"]}, "16312566032010s": {"submission": "2010", "time": 1631256603, "score": 30.0, "extra": ["0", "0", "30", "0", "0", "0"]}, "16312566162011s": {"submission": "2011", "time": 1631256616, "score": 0.0, "extra": ["0", "0", "0", "0", "0", "0"]}, "16312566242012s": {"submission": "2012", "time": 1631256624, "score": 0.0, "extra": ["0", "0", "0", "0", "0", "0", "0", "0", "0"]}, "16312566862013s": {"submission": "2013", "time": 1631256686, "score": 13.0, "extra": ["0", "4", "9", "0", "0", "0"]}, "16312567082014s": {"submission": "2014", "time": 1631256708, "score": 0.0, "extra": ["0", "0", "0", "0", "0", "0"]}, "16312567312015s": {"submission": "2015", "time": 1631256731, "score": 0.0, "extra": ["0", "0", "0", "0", "0", "0"]}, "16312567512016s": {"submission": "2016", "time": 1631256751, "score": 0.0, "extra": ["0", "0", "0", "0", "0", "0"]}, "16312567632017s": {"submission": "2017", "time": 1631256763, "score": 1.0, "extra": ["0", "0", "1", "0", "0", "0", "0", "0", "0"]}, "16312568052018s": {"submission": "2018", "time": 1631256805, "score": 13.0, "extra": ["0", "4", "9", "0", "0", "0"]}, "16312568082019s": {"submission": "2019", "time": 1631256808, "score": 30.0, "extra": ["0", "0", "30", "0", "0", "0"]}, "16312568202020s": {"submission": "2020", "time": 1631256820, "score": 0.0, "extra": ["0", "0", "0", "0", "0", "0"]}, "16312568392021s": {"submission": "2021", "time": 1631256839, "score": 0.0, "extra": ["0", "0", "0", "0", "0", "0"]}, "16312568532022s": {"submission": "2022", "time": 1631256853, "score": 13.0, "extra": ["0", "4", "9", "0", "0", "0"]}, "16312568802023s": {"submission": "2023", "time": 1631256880, "score": 0.0, "extra": ["0", "0", "0", "0", "0", "0"]}, "16312569112024s": {"submission": "2024", "time": 1631256911, "score": 0.0, "extra": ["0", "0", "0", "0", "0", "0"]}, "16312569212025s": {"submission": "2025", "time": 1631256921, "score": 18.0, "extra": ["0", "18", "0", "0", "0", "0"]}, "16312569462026s": {"submission": "2026", "time": 1631256946, "score": 0.0, "extra": ["0", "0", "0", "0", "0", "0"]}, "16312569622027s": {"submission": "2027", "time": 1631256962, "score": 30.0, "extra": ["0", "0", "30", "0", "0", "0"]}, "16312569912028s": {"submission": "2028", "time": 1631256991, "score": 0.0, "extra": ["0", "0", "0", "0", "0", "0"]}, "16312569932029s": {"submission": "2029", "time": 1631256993, "score": 13.0, "extra": ["0", "4", "9", "0", "0", "0"]}, "16312570232030s": {"submission": "2030", "time": 1631257023, "score": 0.0, "extra": ["0", "0", "0", "0", "0", "0"]}, "16312570282031s": {"submission": "2031", "time": 1631257028, "score": 0.0, "extra": ["0", "0", "0", "0", "0"]}, "16312570782032s": {"submission": "2032", "time": 1631257078, "score": 0.0, "extra": ["0", "0", "0", "0", "0", "0"]}, "16312570792033s": {"submission": "2033", "time": 1631257079, "score": 4.0, "extra": ["0", "4", "0", "0", "0", "0"]}, "16312571112034s": {"submission": "2034", "time": 1631257111, "score": 0.0, "extra": ["0", "0", "0", "0", "0", "0"]}, "16312571232035s": {"submission": "2035", "time": 1631257123, "score": 31.0, "extra": ["0", "0", "0", "31", "0", "0"]}, "16312571462036s": {"submission": "2036", "time": 1631257146, "score": 56.0, "extra": ["0", "0", "0", "56", "0"]}, "16312571762037s": {"submission": "2037", "time": 1631257176, "score": 30.0, "extra": ["0", "0", "30", "0", "0", "0"]}, "16312572202038s": {"submission": "2038", "time": 1631257220, "score": 0.0, "extra": ["0", "0", "0", "0", "0", "0"]}, "16312572392039s": {"submission": "2039", "time": 1631257239, "score": 10.0, "extra": ["0", "10", "0", "0", "0", "0"]}, "16312572582040s": {"submission": "2040", "time": 1631257258, "score": 0.0, "extra": ["0", "0", "0", "0", "0", "0"]}, "16312572722041s": {"submission": "2041", "time": 1631257272, "score": 100.0, "extra": ["0", "10", "30", "10", "10", "40"]}, "16312572772042s": {"submission": "2042", "time": 1631257277, "score": 0.0, "extra": ["0", "0", "0", "0", "0", "0"]}, "16312572872044s": {"submission": "2044", "time": 1631257287, "score": 18.0, "extra": ["0", "18", "0", "0", "0", "0"]}, "16312572862043s": {"submission": "2043", "time": 1631257286, "score": 0.0, "extra": ["0", "0", "0", "0", "0", "0"]}, "16312572912045s": {"submission": "2045", "time": 1631257291, "score": 100.0, "extra": ["0", "8", "12", "56", "24"]}, "16312572952046s": {"submission": "2046", "time": 1631257295, "score": 0.0, "extra": ["0", "0", "0", "0", "0", "0"]}, "16312572952047s": {"submission": "2047", "time": 1631257295, "score": 0.0, "extra": ["0", "0", "0", "0", "0", "0"]}, "16312572982048s": {"submission": "2048", "time": 1631257298, "score": 0.0, "extra": ["0", "0", "0", "0", "0", "0"]}, "16312573232049s": {"submission": "2049", "time": 1631257323, "score": 100.0, "extra": ["100"]}, "16312573302050s": {"submission": "2050", "time": 1631257330, "score": 0.0, "extra": ["0", "0", "0", "0", "0", "0", "0", "0", "0"]}, "16312573662051s": {"submission": "2051", "time": 1631257366, "score": 0.0, "extra": ["0", "0", "0", "0", "0", "0"]}, "16312574092052s": {"submission": "2052", "time": 1631257409, "score": 0.0, "extra": ["0", "0", "0", "0", "0", "0"]}, "16312574142053s": {"submission": "2053", "time": 1631257414, "score": 56.0, "extra": ["0", "0", "0", "56", "0"]}, "16312574282054s": {"submission": "2054", "time": 1631257428, "score": 0.0, "extra": ["0", "0", "0", "0", "0", "0"]}, "16312574572056s": {"submission": "2056", "time": 1631257457, "score": 12.0, "extra": ["0", "0", "12", "0", "0"]}, "16312574542055s": {"submission": "2055", "time": 1631257454, "score": 6.0, "extra": ["0", "6", "0", "0", "0"]}, "16312574732058s": {"submission": "2058", "time": 1631257473, "score": 9.0, "extra": ["0", "0", "0", "6", "3", "0", "0", "0", "0"]}, "16312574722057s": {"submission": "2057", "time": 1631257472, "score": 0.0, "extra": ["0", "0", "0", "0", "0", "0"]}, "16312574852059s": {"submission": "2059", "time": 1631257485, "score": 0.0, "extra": ["0", "0", "0", "0", "0", "0"]}, "16312574932060s": {"submission": "2060", "time": 1631257493, "score": 0.0, "extra": ["0", "0", "0", "0", "0"]}, "16312575542061s": {"submission": "2061", "time": 1631257554, "score": 0.0, "extra": ["0", "0", "0", "0", "0", "0"]}, "16312575952062s": {"submission": "2062", "time": 1631257595, "score": 0.0, "extra": ["0", "0", "0", "0", "0", "0"]}, "16312576102063s": {"submission": "2063", "time": 1631257610, "score": 0.0, "extra": ["0", "0", "0", "0", "0", "0"]}, "16312576422064s": {"submission": "2064", "time": 1631257642, "score": 18.0, "extra": ["0", "18", "0", "0", "0", "0"]}, "16312576512065s": {"submission": "2065", "time": 1631257651, "score": 60.0, "extra": ["0", "10", "30", "10", "10", "0"]}, "16312576712066s": {"submission": "2066", "time": 1631257671, "score": 0.0, "extra": ["0", "0", "0", "0", "0", "0"]}, "16312576942067s": {"submission": "2067", "time": 1631257694, "score": 0.0, "extra": ["0", "0", "0", "0", "0", "0"]}, "16312577012068s": {"submission": "2068", "time": 1631257701, "score": 0.0, "extra": ["0", "0", "0", "0", "0"]}, "16312577602069s": {"submission": "2069", "time": 1631257760, "score": 0.0, "extra": ["0", "0", "0", "0", "0", "0"]}, "16312577812070s": {"submission": "2070", "time": 1631257781, "score": 0.0, "extra": ["0", "0", "0", "0", "0", "0"]}, "16312578012071s": {"submission": "2071", "time": 1631257801, "score": 10.0, "extra": ["0", "0", "1", "6", "3", "0", "0", "0", "0"]}, "16312578012072s": {"submission": "2072", "time": 1631257801, "score": 13.0, "extra": ["0", "4", "9", "0", "0", "0"]}, "16312578152074s": {"submission": "2074", "time": 1631257815, "score": 10.0, "extra": ["0", "10", "0", "0", "0", "0"]}, "16312578162075s": {"submission": "2075", "time": 1631257816, "score": 10.0, "extra": ["0", "10", "0", "0", "0", "0"]}, "16312578112073s": {"submission": "2073", "time": 1631257811, "score": 7.0, "extra": ["0", "0", "7", "0", "0"]}, "16312578572076s": {"submission": "2076", "time": 1631257857, "score": 18.0, "extra": ["0", "18", "0", "0", "0", "0"]}, "16312579132077s": {"submission": "2077", "time": 1631257913, "score": 31.0, "extra": ["0", "0", "0", "31", "0", "0"]}, "16312579502078s": {"submission": "2078", "time": 1631257950, "score": 56.0, "extra": ["0", "0", "0", "56", "0"]}, "16312579942079s": {"submission": "2079", "time": 1631257994, "score": 0.0, "extra": ["0", "0", "0", "0", "0", "0"]}, "16312579962080s": {"submission": "2080", "time": 1631257996, "score": 60.0, "extra": ["0", "10", "30", "10", "10", "0"]}, "16312580032082s": {"submission": "2082", "time": 1631258003, "score": 100.0, "extra": ["0", "10", "30", "10", "10", "40"]}, "16312579982081s": {"submission": "2081", "time": 1631257998, "score": 0.0, "extra": ["0", "0", "0", "0", "0", "0"]}, "16312580202083s": {"submission": "2083", "time": 1631258020, "score": 0.0, "extra": ["0", "0", "0", "0", "0", "0"]}, "16312580442084s": {"submission": "2084", "time": 1631258044, "score": 64.0, "extra": ["0", "8", "0", "56", "0"]}, "16312581292085s": {"submission": "2085", "time": 1631258129, "score": 13.0, "extra": ["0", "4", "9", "0", "0", "0"]}, "16312581372086s": {"submission": "2086", "time": 1631258137, "score": 0.0, "extra": ["0", "0", "0", "0", "0", "0"]}, "16312581442087s": {"submission": "2087", "time": 1631258144, "score": 13.0, "extra": ["0", "4", "9", "0", "0", "0"]}, "16312581802088s": {"submission": "2088", "time": 1631258180, "score": 0.0, "extra": ["0", "0", "0", "0", "0", "0"]}, "16312582572089s": {"submission": "2089", "time": 1631258257, "score": 56.0, "extra": ["0", "0", "0", "56", "0"]}, "16312582602090s": {"submission": "2090", "time": 1631258260, "score": 13.0, "extra": ["0", "4", "9", "0", "0", "0"]}, "16312582662091s": {"submission": "2091", "time": 1631258266, "score": 13.0, "extra": ["0", "4", "9", "0", "0", "0"]}, "16312582792092s": {"submission": "2092", "time": 1631258279, "score": 0.0, "extra": ["0", "0", "0", "0", "0", "0"]}, "16312582842093s": {"submission": "2093", "time": 1631258284, "score": 10.0, "extra": ["0", "10", "0", "0", "0", "0"]}, "16312583302094s": {"submission": "2094", "time": 1631258330, "score": 13.0, "extra": ["0", "4", "9", "0", "0", "0"]}, "16312583392095s": {"submission": "2095", "time": 1631258339, "score": 30.0, "extra": ["0", "0", "30", "0", "0", "0"]}, "16312583472096s": {"submission": "2096", "time": 1631258347, "score": 0.0, "extra": ["0", "0", "0", "0", "0", "0", "0", "0", "0"]}, "16312583552097s": {"submission": "2097", "time": 1631258355, "score": 10.0, "extra": ["0", "0", "1", "6", "3", "0", "0", "0", "0"]}, "16312583782098s": {"submission": "2098", "time": 1631258378, "score": 0.0, "extra": ["0", "0", "0", "0", "0", "0"]}, "16312583882099s": {"submission": "2099", "time": 1631258388, "score": 0.0, "extra": ["0", "0", "0", "0", "0", "0"]}, "16312584182100s": {"submission": "2100", "time": 1631258418, "score": 18.0, "extra": ["0", "18", "0", "0", "0", "0"]}, "16312584222101s": {"submission": "2101", "time": 1631258422, "score": 0.0, "extra": ["0", "0", "0", "0", "0", "0"]}, "16312584362102s": {"submission": "2102", "time": 1631258436, "score": 0.0, "extra": ["0", "0", "0", "0", "0"]}, "16312584492103s": {"submission": "2103", "time": 1631258449, "score": 18.0, "extra": ["0", "18", "0", "0", "0", "0"]}, "16312584872104s": {"submission": "2104", "time": 1631258487, "score": 0.0, "extra": ["0", "0", "0", "0", "0", "0"]}, "16312584982105s": {"submission": "2105", "time": 1631258498, "score": 0.0, "extra": ["0", "0", "0", "0", "0", "0"]}, "16312585042106s": {"submission": "2106", "time": 1631258504, "score": 0.0, "extra": ["0", "0", "0", "0", "0"]}, "16312585192107s": {"submission": "2107", "time": 1631258519, "score": 10.0, "extra": ["0", "10", "0", "0", "0", "0"]}, "16312585292108s": {"submission": "2108", "time": 1631258529, "score": 30.0, "extra": ["0", "0", "30", "0", "0", "0"]}, "16312585632109s": {"submission": "2109", "time": 1631258563, "score": 9.0, "extra": ["0", "0", "0", "6", "3", "0", "0", "0", "0"]}, "16312586182110s": {"submission": "2110", "time": 1631258618, "score": 13.0, "extra": ["0", "4", "9", "0", "0", "0"]}, "16312586192111s": {"submission": "2111", "time": 1631258619, "score": 0.0, "extra": ["0", "0", "0", "0", "0", "0", "0", "0", "0"]}, "16312586262113s": {"submission": "2113", "time": 1631258626, "score": 0.0, "extra": ["0", "0", "0", "0", "0"]}, "16312586342114s": {"submission": "2114", "time": 1631258634, "score": 0.0, "extra": ["0", "0", "0", "0", "0", "0"]}, "16312586412115s": {"submission": "2115", "time": 1631258641, "score": 0.0, "extra": ["0", "0", "0", "0", "0", "0"]}, "16312586242112s": {"submission": "2112", "time": 1631258624, "score": 0.0, "extra": ["0", "0", "0", "0", "0", "0"]}, "16312586492116s": {"submission": "2116", "time": 1631258649, "score": 0.0, "extra": ["0", "0", "0", "0", "0", "0"]}, "16312587262117s": {"submission": "2117", "time": 1631258726, "score": 0.0, "extra": ["0", "0", "0", "0", "0", "0"]}, "16312587732118s": {"submission": "2118", "time": 1631258773, "score": 18.0, "extra": ["0", "18", "0", "0", "0", "0"]}, "16312587762119s": {"submission": "2119", "time": 1631258776, "score": 0.0, "extra": ["0", "0", "0", "0", "0"]}, "16312587882120s": {"submission": "2120", "time": 1631258788, "score": 0.0, "extra": ["0", "0", "0", "0", "0", "0", "0", "0", "0"]}, "16312587972121s": {"submission": "2121", "time": 1631258797, "score": 0.0, "extra": ["0", "0", "0", "0", "0", "0", "0", "0", "0"]}, "16312588052122s": {"submission": "2122", "time": 1631258805, "score": 10.0, "extra": ["0", "0", "1", "6", "3", "0", "0", "0", "0"]}, "16312588132123s": {"submission": "2123", "time": 1631258813, "score": 31.0, "extra": ["0", "0", "0", "31", "0", "0"]}, "16312588422124s": {"submission": "2124", "time": 1631258842, "score": 0.0, "extra": ["0", "0", "0", "0", "0"]}, "16312588572125s": {"submission": "2125", "time": 1631258857, "score": 18.0, "extra": ["0", "18", "0", "0", "0", "0"]}, "16312588742126s": {"submission": "2126", "time": 1631258874, "score": 0.0, "extra": ["0", "0", "0", "0", "0", "0"]}, "16312588892127s": {"submission": "2127", "time": 1631258889, "score": 0.0, "extra": ["0", "0", "0", "0", "0", "0"]}, "16312589592128s": {"submission": "2128", "time": 1631258959, "score": 0.0, "extra": ["0", "0", "0", "0", "0", "0", "0", "0", "0"]}, "16312589622129s": {"submission": "2129", "time": 1631258962, "score": 0.0, "extra": ["0", "0", "0", "0", "0"]}, "16312589762130s": {"submission": "2130", "time": 1631258976, "score": 0.0, "extra": ["0", "0", "0", "0", "0"]}, "16312589872131s": {"submission": "2131", "time": 1631258987, "score": 64.0, "extra": ["0", "8", "0", "56", "0"]}, "16312589902133s": {"submission": "2133", "time": 1631258990, "score": 31.0, "extra": ["0", "0", "0", "31", "0", "0"]}, "16312589902132s": {"submission": "2132", "time": 1631258990, "score": 0.0, "extra": ["0", "0", "0", "0", "0", "0"]}, "16312590152134s": {"submission": "2134", "time": 1631259015, "score": 76.0, "extra": ["0", "8", "12", "56", "0"]}, "16312590612135s": {"submission": "2135", "time": 1631259061, "score": 0.0, "extra": ["0", "0", "0", "0", "0", "0"]}, "16312590762136s": {"submission": "2136", "time": 1631259076, "score": 18.0, "extra": ["0", "18", "0", "0", "0", "0"]}, "16312591012137s": {"submission": "2137", "time": 1631259101, "score": 0.0, "extra": ["0", "0", "0", "0", "0"]}, "16312591012138s": {"submission": "2138", "time": 1631259101, "score": 0.0, "extra": ["0", "0", "0", "0", "0", "0", "0", "0", "0"]}, "16312591112139s": {"submission": "2139", "time": 1631259111, "score": 0.0, "extra": ["0", "0", "0", "0", "0", "0"]}, "16312591722140s": {"submission": "2140", "time": 1631259172, "score": 0.0, "extra": ["0", "0", "0", "0", "0", "0"]}, "16312592192141s": {"submission": "2141", "time": 1631259219, "score": 0.0, "extra": ["0", "0", "0", "0", "0"]}, "16312592262142s": {"submission": "2142", "time": 1631259226, "score": 18.0, "extra": ["0", "18", "0", "0", "0", "0"]}, "16312592692143s": {"submission": "2143", "time": 1631259269, "score": 0.0, "extra": ["0", "0", "0", "0", "0", "0"]}, "16312592712144s": {"submission": "2144", "time": 1631259271, "score": 1.0, "extra": ["0", "0", "1", "0", "0", "0", "0", "0", "0"]}, "16312592762145s": {"submission": "2145", "time": 1631259276, "score": 0.0, "extra": ["0", "0", "0", "0", "0", "0"]}, "16312593112146s": {"submission": "2146", "time": 1631259311, "score": 18.0, "extra": ["0", "18", "0", "0", "0", "0"]}, "16312593302147s": {"submission": "2147", "time": 1631259330, "score": 0.0, "extra": ["0", "0", "0", "0", "0", "0"]}, "16312593722148s": {"submission": "2148", "time": 1631259372, "score": 10.0, "extra": ["0", "10", "0", "0", "0", "0"]}, "16312593752149s": {"submission": "2149", "time": 1631259375, "score": 0.0, "extra": ["0", "0", "0", "0", "0", "0"]}, "16312594522150s": {"submission": "2150", "time": 1631259452, "score": 0.0, "extra": ["0", "0", "0", "0", "0", "0"]}, "16312594602151s": {"submission": "2151", "time": 1631259460, "score": 0.0, "extra": ["0", "0", "0", "0", "0", "0"]}, "16312594632152s": {"submission": "2152", "time": 1631259463, "score": 0.0, "extra": ["0", "0", "0", "0", "0"]}, "16312594782153s": {"submission": "2153", "time": 1631259478, "score": 9.0, "extra": ["0", "0", "9", "0", "0", "0"]}, "16312594832154s": {"submission": "2154", "time": 1631259483, "score": 30.0, "extra": ["0", "0", "30", "0", "0", "0"]}, "16312594902155s": {"submission": "2155", "time": 1631259490, "score": 100.0, "extra": ["0", "10", "30", "10", "10", "40"]}, "16312595112156s": {"submission": "2156", "time": 1631259511, "score": 0.0, "extra": ["0", "0", "0", "0", "0", "0"]}, "16312595112157s": {"submission": "2157", "time": 1631259511, "score": 0.0, "extra": ["0", "0", "0", "0", "0", "0"]}, "16312595262158s": {"submission": "2158", "time": 1631259526, "score": 30.0, "extra": ["0", "0", "30", "0", "0", "0"]}, "16312595452159s": {"submission": "2159", "time": 1631259545, "score": 12.0, "extra": ["0", "0", "0", "0", "0", "12", "0", "0", "0"]}, "16312595832160s": {"submission": "2160", "time": 1631259583, "score": 0.0, "extra": ["0", "0", "0", "0", "0"]}, "16312595872161s": {"submission": "2161", "time": 1631259587, "score": 0.0, "extra": ["0", "0", "0", "0", "0", "0"]}, "16312596052162s": {"submission": "2162", "time": 1631259605, "score": 0.0, "extra": ["0", "0", "0", "0", "0", "0", "0", "0", "0"]}, "16312596132164s": {"submission": "2164", "time": 1631259613, "score": 35.0, "extra": ["0", "0", "1", "6", "3", "12", "13", "0", "0"]}, "16312596092163s": {"submission": "2163", "time": 1631259609, "score": 0.0, "extra": ["0", "0", "0", "0", "0", "0"]}, "16312596232165s": {"submission": "2165", "time": 1631259623, "score": 64.0, "extra": ["0", "8", "0", "56", "0"]}, "16312596342166s": {"submission": "2166", "time": 1631259634, "score": 0.0, "extra": ["0", "0", "0", "0", "0", "0"]}, "16312596722167s": {"submission": "2167", "time": 1631259672, "score": 32.0, "extra": ["0", "0", "1", "6", "0", "12", "13", "0", "0"]}, "16312596852170s": {"submission": "2170", "time": 1631259685, "score": 0.0, "extra": ["0", "0", "0", "0", "0"]}, "16312596882171s": {"submission": "2171", "time": 1631259688, "score": 31.0, "extra": ["0", "0", "0", "31", "0", "0"]}, "16312596822169s": {"submission": "2169", "time": 1631259682, "score": 0.0, "extra": ["0", "0", "0", "0", "0", "0"]}, "16312597292172s": {"submission": "2172", "time": 1631259729, "score": 0.0, "extra": ["0", "0", "0", "0", "0", "0"]}, "16312597302173s": {"submission": "2173", "time": 1631259730, "score": 0.0, "extra": ["0", "0", "0", "0", "0", "0"]}, "16312598052176s": {"submission": "2176", "time": 1631259805, "score": 0.0, "extra": ["0", "0", "0", "0", "0"]}, "16312598022174s": {"submission": "2174", "time": 1631259802, "score": 25.0, "extra": ["0", "0", "0", "0", "0", "12", "13", "0", "0"]}, "16312598042175s": {"submission": "2175", "time": 1631259804, "score": 30.0, "extra": ["0", "0", "30", "0", "0", "0"]}, "16312598222177s": {"submission": "2177", "time": 1631259822, "score": 56.0, "extra": ["0", "0", "0", "56", "0"]}, "16312598532178s": {"submission": "2178", "time": 1631259853, "score": 31.0, "extra": ["0", "0", "0", "31", "0", "0"]}, "16312598572179s": {"submission": "2179", "time": 1631259857, "score": 0.0, "extra": ["0", "0", "0", "0", "0"]}, "16312598812180s": {"submission": "2180", "time": 1631259881, "score": 100.0, "extra": ["0", "8", "12", "56", "24"]}, "16312598972181s": {"submission": "2181", "time": 1631259897, "score": 0.0, "extra": ["0", "0", "0", "0", "0", "0"]}, "16312599052182s": {"submission": "2182", "time": 1631259905, "score": 0.0, "extra": ["0", "0", "0", "0", "0", "0"]}, "16312599372183s": {"submission": "2183", "time": 1631259937, "score": 31.0, "extra": ["0", "0", "0", "31", "0", "0"]}, "16312599622185s": {"submission": "2185", "time": 1631259962, "score": 0.0, "extra": ["0", "0", "0", "0", "0"]}, "16312599612184s": {"submission": "2184", "time": 1631259961, "score": 0.0, "extra": ["0", "0", "0", "0", "0", "0"]}, "16312599722186s": {"submission": "2186", "time": 1631259972, "score": 0.0, "extra": ["0", "0", "0", "0", "0", "0", "0", "0", "0"]}, "16312600052187s": {"submission": "2187", "time": 1631260005, "score": 31.0, "extra": ["0", "0", "0", "31", "0", "0"]}, "16312600412188s": {"submission": "2188", "time": 1631260041, "score": 0.0, "extra": ["0", "0", "0", "0", "0", "0"]}, "16312600572189s": {"submission": "2189", "time": 1631260057, "score": 100.0, "extra": ["0", "10", "30", "10", "10", "40"]}, "16312600622190s": {"submission": "2190", "time": 1631260062, "score": 13.0, "extra": ["0", "6", "7", "0", "0"]}, "16312600642191s": {"submission": "2191", "time": 1631260064, "score": 0.0, "extra": ["0", "0", "0", "0", "0", "0"]}, "16312600712192s": {"submission": "2192", "time": 1631260071, "score": 0.0, "extra": ["0", "0", "0", "0", "0", "0"]}, "16312601102193s": {"submission": "2193", "time": 1631260110, "score": 100.0, "extra": ["0", "8", "12", "56", "24"]}, "16312601132194s": {"submission": "2194", "time": 1631260113, "score": 18.0, "extra": ["0", "18", "0", "0", "0", "0"]}, "16312601262195s": {"submission": "2195", "time": 1631260126, "score": 31.0, "extra": ["0", "0", "0", "31", "0", "0"]}, "16312601292196s": {"submission": "2196", "time": 1631260129, "score": 0.0, "extra": ["0", "0", "0", "0", "0", "0"]}, "16312601742197s": {"submission": "2197", "time": 1631260174, "score": 0.0, "extra": ["0", "0", "0", "0", "0", "0"]}, "16312602032198s": {"submission": "2198", "time": 1631260203, "score": 0.0, "extra": ["0", "0", "0", "0", "0", "0"]}, "16312602172199s": {"submission": "2199", "time": 1631260217, "score": 100.0, "extra": ["0", "8", "12", "56", "24"]}, "16312602312200s": {"submission": "2200", "time": 1631260231, "score": 13.0, "extra": ["0", "4", "9", "0", "0", "0"]}, "16312602472201s": {"submission": "2201", "time": 1631260247, "score": 31.0, "extra": ["0", "0", "0", "31", "0", "0"]}, "16312602712202s": {"submission": "2202", "time": 1631260271, "score": 13.0, "extra": ["0", "4", "9", "0", "0", "0"]}, "16312603352203s": {"submission": "2203", "time": 1631260335, "score": 0.0, "extra": ["0", "0", "0", "0", "0", "0"]}, "16312603642204s": {"submission": "2204", "time": 1631260364, "score": 0.0, "extra": ["0", "0", "0", "0", "0"]}, "16312603652205s": {"submission": "2205", "time": 1631260365, "score": 35.0, "extra": ["0", "0", "1", "6", "3", "12", "13", "0", "0"]}, "16312603732207s": {"submission": "2207", "time": 1631260373, "score": 25.0, "extra": ["0", "0", "0", "0", "0", "12", "13", "0", "0"]}, "16312603762208s": {"submission": "2208", "time": 1631260376, "score": 31.0, "extra": ["0", "0", "0", "31", "0", "0"]}, "16312603702206s": {"submission": "2206", "time": 1631260370, "score": 0.0, "extra": ["0", "0", "0", "0", "0", "0"]}, "16312603852209s": {"submission": "2209", "time": 1631260385, "score": 18.0, "extra": ["0", "18", "0", "0", "0", "0"]}, "16312604062210s": {"submission": "2210", "time": 1631260406, "score": 0.0, "extra": ["0", "0", "0", "0", "0", "0"]}, "16312604242211s": {"submission": "2211", "time": 1631260424, "score": 0.0, "extra": ["0", "0", "0", "0", "0", "0"]}, "16312604312212s": {"submission": "2212", "time": 1631260431, "score": 0.0, "extra": ["0", "0", "0", "0", "0", "0"]}, "16312604972213s": {"submission": "2213", "time": 1631260497, "score": 31.0, "extra": ["0", "0", "0", "31", "0", "0"]}, "16312604972214s": {"submission": "2214", "time": 1631260497, "score": 60.0, "extra": ["0", "10", "30", "10", "10", "0"]}, "16312605102215s": {"submission": "2215", "time": 1631260510, "score": 0.0, "extra": ["0", "0", "0", "0", "0", "0"]}, "16312605732216s": {"submission": "2216", "time": 1631260573, "score": 18.0, "extra": ["0", "18", "0", "0", "0", "0"]}, "16312605752217s": {"submission": "2217", "time": 1631260575, "score": 0.0, "extra": ["0", "0", "0", "0", "0", "0"]}, "16312605862219s": {"submission": "2219", "time": 1631260586, "score": 35.0, "extra": ["0", "0", "1", "6", "3", "12", "13", "0", "0"]}, "16312605812218s": {"submission": "2218", "time": 1631260581, "score": 18.0, "extra": ["0", "18", "0", "0", "0", "0"]}, "16312605952220s": {"submission": "2220", "time": 1631260595, "score": 0.0, "extra": ["0", "0", "0", "0", "0", "0"]}, "16312606322222s": {"submission": "2222", "time": 1631260632, "score": 0.0, "extra": ["0", "0", "0", "0", "0", "0"]}, "16312606182221s": {"submission": "2221", "time": 1631260618, "score": 31.0, "extra": ["0", "0", "0", "31", "0", "0"]}, "16312606572223s": {"submission": "2223", "time": 1631260657, "score": 0.0, "extra": ["0", "0", "0", "0", "0", "0"]}, "16312606592224s": {"submission": "2224", "time": 1631260659, "score": 4.0, "extra": ["0", "4", "0", "0", "0", "0"]}, "16312606612225s": {"submission": "2225", "time": 1631260661, "score": 31.0, "extra": ["0", "0", "0", "31", "0", "0"]}, "16312607392226s": {"submission": "2226", "time": 1631260739, "score": 31.0, "extra": ["0", "0", "0", "31", "0", "0"]}, "16312607572227s": {"submission": "2227", "time": 1631260757, "score": 0.0, "extra": ["0", "0", "0", "0", "0", "0"]}, "16312607702228s": {"submission": "2228", "time": 1631260770, "score": 0.0, "extra": ["0", "0", "0", "0", "0", "0"]}, "16312607812229s": {"submission": "2229", "time": 1631260781, "score": 18.0, "extra": ["0", "18", "0", "0", "0", "0"]}, "16312608182230s": {"submission": "2230", "time": 1631260818, "score": 0.0, "extra": ["0", "0", "0", "0", "0", "0"]}, "16312608182231s": {"submission": "2231", "time": 1631260818, "score": 4.0, "extra": ["0", "4", "0", "0", "0", "0"]}, "16312608522232s": {"submission": "2232", "time": 1631260852, "score": 0.0, "extra": ["0", "0", "0", "0", "0", "0"]}, "16312608702233s": {"submission": "2233", "time": 1631260870, "score": 0.0, "extra": ["0", "0", "0", "0", "0"]}, "16312608922234s": {"submission": "2234", "time": 1631260892, "score": 18.0, "extra": ["0", "18", "0", "0", "0", "0"]}, "16312609392236s": {"submission": "2236", "time": 1631260939, "score": 0.0, "extra": ["0", "0", "0", "0", "0"]}, "16312609392235s": {"submission": "2235", "time": 1631260939, "score": 0.0, "extra": ["0", "0", "0", "0", "0", "0"]}, "16312609602237s": {"submission": "2237", "time": 1631260960, "score": 31.0, "extra": ["0", "0", "0", "31", "0", "0"]}, "16312609722238s": {"submission": "2238", "time": 1631260972, "score": 0.0, "extra": ["0", "0", "0", "0", "0", "0"]}, "16312609812239s": {"submission": "2239", "time": 1631260981, "score": 22.0, "extra": ["0", "22", "0", "0", "0", "0", "0", "0", "0"]}, "16312610102240s": {"submission": "2240", "time": 1631261010, "score": 92.0, "extra": ["0", "0", "12", "56", "24"]}, "16312610322242s": {"submission": "2242", "time": 1631261032, "score": 100.0, "extra": ["100"]}, "16312610312241s": {"submission": "2241", "time": 1631261031, "score": 0.0, "extra": ["0", "0", "0", "0", "0", "0"]}, "16312610502243s": {"submission": "2243", "time": 1631261050, "score": 18.0, "extra": ["0", "18", "0", "0", "0", "0"]}, "16312610672244s": {"submission": "2244", "time": 1631261067, "score": 0.0, "extra": ["0", "0", "0", "0", "0"]}, "16312610812245s": {"submission": "2245", "time": 1631261081, "score": 31.0, "extra": ["0", "0", "0", "31", "0", "0"]}, "16312610912246s": {"submission": "2246", "time": 1631261091, "score": 13.0, "extra": ["0", "4", "9", "0", "0", "0"]}, "16312611042247s": {"submission": "2247", "time": 1631261104, "score": 0.0, "extra": ["0", "0", "0", "0", "0", "0"]}, "16312611312248s": {"submission": "2248", "time": 1631261131, "score": 100.0, "extra": ["0", "8", "12", "56", "24"]}, "16312611992249s": {"submission": "2249", "time": 1631261199, "score": 4.0, "extra": ["0", "4", "0", "0", "0", "0"]}, "16312612032251s": {"submission": "2251", "time": 1631261203, "score": 31.0, "extra": ["0", "0", "0", "31", "0", "0"]}, "16312612002250s": {"submission": "2250", "time": 1631261200, "score": 13.0, "extra": ["0", "6", "7", "0", "0"]}, "16312612172252s": {"submission": "2252", "time": 1631261217, "score": 100.0, "extra": ["0", "8", "12", "56", "24"]}, "16312612322253s": {"submission": "2253", "time": 1631261232, "score": 35.0, "extra": ["0", "0", "1", "6", "3", "12", "13", "0", "0"]}, "16312612852254s": {"submission": "2254", "time": 1631261285, "score": 0.0, "extra": ["0", "0", "0", "0", "0", "0"]}, "16312613262255s": {"submission": "2255", "time": 1631261326, "score": 0.0, "extra": ["0", "0", "0", "0", "0", "0"]}, "16312613452256s": {"submission": "2256", "time": 1631261345, "score": 6.0, "extra": ["0", "6", "0", "0", "0"]}, "16312613562257s": {"submission": "2257", "time": 1631261356, "score": 1.0, "extra": ["0", "0", "1", "0", "0", "0", "0", "0", "0"]}, "16312613572258s": {"submission": "2258", "time": 1631261357, "score": 18.0, "extra": ["0", "18", "0", "0", "0", "0"]}, "16312614102259s": {"submission": "2259", "time": 1631261410, "score": 100.0, "extra": ["0", "18", "8", "14", "39", "21"]}, "16312614472260s": {"submission": "2260", "time": 1631261447, "score": 0.0, "extra": ["0", "0", "0", "0", "0", "0"]}, "16312614472261s": {"submission": "2261", "time": 1631261447, "score": 0.0, "extra": ["0", "0", "0", "0", "0", "0"]}, "16312614552262s": {"submission": "2262", "time": 1631261455, "score": 0.0, "extra": ["0", "0", "0", "0", "0", "0"]}, "16312614792263s": {"submission": "2263", "time": 1631261479, "score": 0.0, "extra": ["0", "0", "0", "0", "0", "0"]}, "16312614852264s": {"submission": "2264", "time": 1631261485, "score": 18.0, "extra": ["0", "18", "0", "0", "0", "0"]}, "16312614902265s": {"submission": "2265", "time": 1631261490, "score": 0.0, "extra": ["0", "0", "0", "0", "0", "0"]}, "16312615142266s": {"submission": "2266", "time": 1631261514, "score": 18.0, "extra": ["0", "18", "0", "0", "0", "0"]}, "16312615402267s": {"submission": "2267", "time": 1631261540, "score": 0.0, "extra": ["0", "0", "0", "0", "0", "0"]}, "16312615952268s": {"submission": "2268", "time": 1631261595, "score": 31.0, "extra": ["0", "0", "0", "31", "0", "0"]}, "16312616272269s": {"submission": "2269", "time": 1631261627, "score": 13.0, "extra": ["0", "4", "9", "0", "0", "0"]}, "16312616352270s": {"submission": "2270", "time": 1631261635, "score": 60.0, "extra": ["0", "10", "30", "10", "10", "0"]}, "16312616382271s": {"submission": "2271", "time": 1631261638, "score": 0.0, "extra": ["0", "0", "0", "0", "0", "0"]}, "16312617022272s": {"submission": "2272", "time": 1631261702, "score": 0.0, "extra": ["0", "0", "0", "0", "0", "0"]}, "16312617132273s": {"submission": "2273", "time": 1631261713, "score": 9.0, "extra": ["0", "0", "0", "6", "3", "0", "0", "0", "0"]}, "16312617182274s": {"submission": "2274", "time": 1631261718, "score": 0.0, "extra": ["0", "0", "0", "0", "0", "0"]}, "16312617222275s": {"submission": "2275", "time": 1631261722, "score": 13.0, "extra": ["0", "4", "9", "0", "0", "0"]}, "16312617512276s": {"submission": "2276", "time": 1631261751, "score": 0.0, "extra": ["0", "0", "0", "0", "0", "0"]}, "16312617762277s": {"submission": "2277", "time": 1631261776, "score": 13.0, "extra": ["0", "4", "9", "0", "0", "0"]}, "16312617772278s": {"submission": "2278", "time": 1631261777, "score": 18.0, "extra": ["0", "18", "0", "0", "0", "0"]}, "16312617842279s": {"submission": "2279", "time": 1631261784, "score": 0.0, "extra": ["0", "0", "0", "0", "0", "0"]}, "16312617912280s": {"submission": "2280", "time": 1631261791, "score": 76.0, "extra": ["0", "8", "12", "56", "0"]}, "16312618102281s": {"submission": "2281", "time": 1631261810, "score": 0.0, "extra": ["0", "0", "0", "0", "0", "0"]}, "16312618152282s": {"submission": "2282", "time": 1631261815, "score": 0.0, "extra": ["0", "0", "0", "0", "0", "0"]}, "16312618592283s": {"submission": "2283", "time": 1631261859, "score": 13.0, "extra": ["0", "4", "9", "0", "0", "0"]}, "16312618802284s": {"submission": "2284", "time": 1631261880, "score": 0.0, "extra": ["0", "0", "0", "0", "0", "0"]}, "16312619042285s": {"submission": "2285", "time": 1631261904, "score": 0.0, "extra": ["0", "0", "0", "0", "0", "0"]}, "16312619082286s": {"submission": "2286", "time": 1631261908, "score": 31.0, "extra": ["0", "0", "0", "31", "0", "0"]}, "16312619332287s": {"submission": "2287", "time": 1631261933, "score": 0.0, "extra": ["0", "0", "0", "0", "0", "0"]}, "16312619522288s": {"submission": "2288", "time": 1631261952, "score": 0.0, "extra": ["0", "0", "0", "0", "0", "0"]}, "16312619612289s": {"submission": "2289", "time": 1631261961, "score": 0.0, "extra": ["0", "0", "0", "0", "0"]}, "16312619692290s": {"submission": "2290", "time": 1631261969, "score": 0.0, "extra": ["0", "0", "0", "0", "0", "0"]}, "16312619872291s": {"submission": "2291", "time": 1631261987, "score": 100.0, "extra": ["0", "10", "30", "10", "10", "40"]}, "16312619902292s": {"submission": "2292", "time": 1631261990, "score": 13.0, "extra": ["0", "6", "7", "0", "0"]}, "16312620072293s": {"submission": "2293", "time": 1631262007, "score": 0.0, "extra": ["0", "0", "0", "0", "0", "0"]}, "16312620552294s": {"submission": "2294", "time": 1631262055, "score": 6.0, "extra": ["0", "0", "0", "6", "0", "0", "0", "0", "0"]}, "16312620792295s": {"submission": "2295", "time": 1631262079, "score": 0.0, "extra": ["0", "0", "0", "0", "0", "0"]}, "16312621172296s": {"submission": "2296", "time": 1631262117, "score": 0.0, "extra": ["0", "0", "0", "0", "0", "0"]}, "16312621192297s": {"submission": "2297", "time": 1631262119, "score": 0.0, "extra": ["0", "0", "0", "0", "0", "0"]}, "16312621352298s": {"submission": "2298", "time": 1631262135, "score": 0.0, "extra": ["0", "0", "0", "0", "0", "0"]}, "16312621552299s": {"submission": "2299", "time": 1631262155, "score": 13.0, "extra": ["0", "4", "9", "0", "0", "0"]}, "16312621562300s": {"submission": "2300", "time": 1631262156, "score": 18.0, "extra": ["0", "18", "0", "0", "0", "0"]}, "16312621882301s": {"submission": "2301", "time": 1631262188, "score": 18.0, "extra": ["0", "18", "0", "0", "0", "0"]}, "16312621992302s": {"submission": "2302", "time": 1631262199, "score": 0.0, "extra": ["0", "0", "0", "0", "0", "0"]}, "16312622042303s": {"submission": "2303", "time": 1631262204, "score": 0.0, "extra": ["0", "0", "0", "0", "0", "0"]}, "16312622182304s": {"submission": "2304", "time": 1631262218, "score": 0.0, "extra": ["0", "0", "0", "0", "0", "0"]}, "16312622252305s": {"submission": "2305", "time": 1631262225, "score": 0.0, "extra": ["0", "0", "0", "0", "0", "0"]}, "16312622402306s": {"submission": "2306", "time": 1631262240, "score": 0.0, "extra": ["0", "0", "0", "0", "0", "0"]}, "16312622452307s": {"submission": "2307", "time": 1631262245, "score": 18.0, "extra": ["0", "18", "0", "0", "0", "0"]}, "16312622452308s": {"submission": "2308", "time": 1631262245, "score": 0.0, "extra": ["0", "0", "0", "0", "0", "0"]}, "16312622522309s": {"submission": "2309", "time": 1631262252, "score": 13.0, "extra": ["0", "4", "9", "0", "0", "0"]}, "16312622552310s": {"submission": "2310", "time": 1631262255, "score": 0.0, "extra": ["0", "0", "0", "0", "0"]}, "16312622872311s": {"submission": "2311", "time": 1631262287, "score": 0.0, "extra": ["0", "0", "0", "0", "0"]}, "16312622892312s": {"submission": "2312", "time": 1631262289, "score": 13.0, "extra": ["0", "6", "7", "0", "0"]}, "16312622982313s": {"submission": "2313", "time": 1631262298, "score": 0.0, "extra": ["0", "0", "0", "0", "0", "0"]}, "16312623222314s": {"submission": "2314", "time": 1631262322, "score": 0.0, "extra": ["0", "0", "0", "0", "0"]}, "16312623282315s": {"submission": "2315", "time": 1631262328, "score": 0.0, "extra": ["0", "0", "0", "0", "0", "0", "0", "0", "0"]}, "16312623402316s": {"submission": "2316", "time": 1631262340, "score": 0.0, "extra": ["0", "0", "0", "0", "0"]}, "16312623422317s": {"submission": "2317", "time": 1631262342, "score": 38.0, "extra": ["0", "0", "1", "6", "0", "12", "0", "19", "0"]}, "16312623532318s": {"submission": "2318", "time": 1631262353, "score": 64.0, "extra": ["0", "8", "0", "56", "0"]}, "16312623552319s": {"submission": "2319", "time": 1631262355, "score": 0.0, "extra": ["0", "0", "0", "0", "0"]}, "16312623572320s": {"submission": "2320", "time": 1631262357, "score": 0.0, "extra": ["0", "0", "0", "0", "0", "0"]}, "16312623622321s": {"submission": "2321", "time": 1631262362, "score": 13.0, "extra": ["0", "4", "9", "0", "0", "0"]}, "16312623672322s": {"submission": "2322", "time": 1631262367, "score": 0.0, "extra": ["0", "0", "0", "0", "0", "0"]}, "16312623722323s": {"submission": "2323", "time": 1631262372, "score": 60.0, "extra": ["0", "10", "30", "10", "10", "0"]}, "16312623842325s": {"submission": "2325", "time": 1631262384, "score": 0.0, "extra": ["0", "0", "0", "0", "0", "0"]}, "16312623742324s": {"submission": "2324", "time": 1631262374, "score": 18.0, "extra": ["0", "18", "0", "0", "0", "0"]}, "16312623912326s": {"submission": "2326", "time": 1631262391, "score": 18.0, "extra": ["0", "18", "0", "0", "0", "0"]}, "16312624022327s": {"submission": "2327", "time": 1631262402, "score": 0.0, "extra": ["0", "0", "0", "0", "0"]}, "16312624102328s": {"submission": "2328", "time": 1631262410, "score": 0.0, "extra": ["0", "0", "0", "0", "0", "0"]}, "16312624122329s": {"submission": "2329", "time": 1631262412, "score": 18.0, "extra": ["0", "18", "0", "0", "0", "0"]}, "16312624142330s": {"submission": "2330", "time": 1631262414, "score": 0.0, "extra": ["0", "0", "0", "0", "0", "0"]}, "16312624162331s": {"submission": "2331", "time": 1631262416, "score": 0.0, "extra": ["0", "0", "0", "0", "0", "0"]}, "16312624382334s": {"submission": "2334", "time": 1631262438, "score": 60.0, "extra": ["0", "10", "30", "10", "10", "0"]}, "16312624492335s": {"submission": "2335", "time": 1631262449, "score": 1.0, "extra": ["0", "0", "1", "0", "0", "0", "0", "0", "0"]}, "16312624332333s": {"submission": "2333", "time": 1631262433, "score": 10.0, "extra": ["0", "10", "0", "0", "0", "0"]}, "16312624222332s": {"submission": "2332", "time": 1631262422, "score": 13.0, "extra": ["0", "4", "9", "0", "0", "0"]}, "16312624552336s": {"submission": "2336", "time": 1631262455, "score": 0.0, "extra": ["0", "0", "0", "0", "0", "0"]}, "16312624652338s": {"submission": "2338", "time": 1631262465, "score": 0.0, "extra": ["0", "0", "0", "0", "0", "0"]}, "16312624632337s": {"submission": "2337", "time": 1631262463, "score": 0.0, "extra": ["0", "0", "0", "0", "0", "0"]}, "16312624652339s": {"submission": "2339", "time": 1631262465, "score": 0.0, "extra": ["0", "0", "0", "0", "0", "0"]}, "16312624732340s": {"submission": "2340", "time": 1631262473, "score": 0.0, "extra": ["0", "0", "0", "0", "0", "0"]}, "16312625152341s": {"submission": "2341", "time": 1631262515, "score": 0.0, "extra": ["0", "0", "0", "0", "0", "0"]}, "16312625362342s": {"submission": "2342", "time": 1631262536, "score": 10.0, "extra": ["0", "10", "0", "0", "0", "0"]}, "16312625452343s": {"submission": "2343", "time": 1631262545, "score": 0.0, "extra": ["0", "0", "0", "0", "0"]}, "16312625462344s": {"submission": "2344", "time": 1631262546, "score": 60.0, "extra": ["0", "10", "30", "10", "10", "0"]}, "16312625512345s": {"submission": "2345", "time": 1631262551, "score": 0.0, "extra": ["0", "0", "0", "0", "0", "0"]}, "16312625522346s": {"submission": "2346", "time": 1631262552, "score": 0.0, "extra": ["0", "0", "0", "0", "0", "0"]}, "16312625572347s": {"submission": "2347", "time": 1631262557, "score": 0.0, "extra": ["0", "0", "0", "0", "0"]}, "16312625622348s": {"submission": "2348", "time": 1631262562, "score": 0.0, "extra": ["0", "0", "0", "0", "0"]}, "16312625682349s": {"submission": "2349", "time": 1631262568, "score": 0.0, "extra": ["0", "0", "0", "0", "0", "0"]}, "16312625772350s": {"submission": "2350", "time": 1631262577, "score": 60.0, "extra": ["0", "10", "30", "10", "10", "0"]}, "16312625902351s": {"submission": "2351", "time": 1631262590, "score": 0.0, "extra": ["0", "0", "0", "0", "0", "0"]}, "16312625952352s": {"submission": "2352", "time": 1631262595, "score": 0.0, "extra": ["0", "0", "0", "0", "0", "0"]}, "16312625962353s": {"submission": "2353", "time": 1631262596, "score": 8.0, "extra": ["0", "8", "0", "0", "0"]}}